README.rst
setup.py
marbaloo_telegram/__init__.py
marbaloo_telegram.egg-info/PKG-INFO
marbaloo_telegram.egg-info/SOURCES.txt
marbaloo_telegram.egg-info/dependency_links.txt
marbaloo_telegram.egg-info/requires.txt
marbaloo_telegram.egg-info/top_level.txt
test/testcase.py